ghs/__init__.py
ghs/async_storage.py
ghs/config.py
ghs/storage.py
pyghs-0.2.3.dist-info/METADATA
pyghs-0.2.3.dist-info/WHEEL
pyghs-0.2.3.dist-info/top_level.txt
pyghs-0.2.3.dist-info/RECORD
