Metadata-Version: 2.1
Name: pyghs
Version: 0.2.3
Summary: Storage csv file in github repository.
Author-email: Chaoying <chaoying2022@gmail.com>
License: MIT
Keywords: github,storage,pandas
Classifier: Programming Language :: Python :: 3
Classifier: Programming Language :: Python :: 3.8
Classifier: Programming Language :: Python :: 3.9
Classifier: Programming Language :: Python :: 3.10
Classifier: Programming Language :: Python :: 3.11
Requires-Python: >=3.8
Requires-Dist: aiohttp (>=3.8.4)
Requires-Dist: pandas (>=2.0.1)
Requires-Dist: dynaconf (>=3.1.12)
Requires-Dist: requests (>=2.29.0)
